honeyhive/__init__.py
honeyhive/py.typed
honeyhive/_generated/__init__.py
honeyhive/_generated/api_config.py
honeyhive/_generated/models/AddDatapointsResponse.py
honeyhive/_generated/models/AddDatapointsToDatasetRequest.py
honeyhive/_generated/models/BatchCreateDatapointsRequest.py
honeyhive/_generated/models/BatchCreateDatapointsResponse.py
honeyhive/_generated/models/CreateConfigurationRequest.py
honeyhive/_generated/models/CreateConfigurationResponse.py
honeyhive/_generated/models/CreateDatapointRequest.py
honeyhive/_generated/models/CreateDatapointResponse.py
honeyhive/_generated/models/CreateDatasetRequest.py
honeyhive/_generated/models/CreateDatasetResponse.py
honeyhive/_generated/models/CreateMetricRequest.py
honeyhive/_generated/models/CreateMetricResponse.py
honeyhive/_generated/models/CreateToolRequest.py
honeyhive/_generated/models/CreateToolResponse.py
honeyhive/_generated/models/DeleteConfigurationResponse.py
honeyhive/_generated/models/DeleteDatapointParams.py
honeyhive/_generated/models/DeleteDatapointResponse.py
honeyhive/_generated/models/DeleteDatasetQuery.py
honeyhive/_generated/models/DeleteDatasetResponse.py
honeyhive/_generated/models/DeleteEventParams.py
honeyhive/_generated/models/DeleteEventResponse.py
honeyhive/_generated/models/DeleteExperimentRunParams.py
honeyhive/_generated/models/DeleteExperimentRunResponse.py
honeyhive/_generated/models/DeleteMetricQuery.py
honeyhive/_generated/models/DeleteMetricResponse.py
honeyhive/_generated/models/DeleteSessionResponse.py
honeyhive/_generated/models/DeleteToolQuery.py
honeyhive/_generated/models/DeleteToolResponse.py
honeyhive/_generated/models/Event.py
honeyhive/_generated/models/GetConfigurationsQuery.py
honeyhive/_generated/models/GetConfigurationsResponse.py
honeyhive/_generated/models/GetDatapointParams.py
honeyhive/_generated/models/GetDatapointResponse.py
honeyhive/_generated/models/GetDatapointsQuery.py
honeyhive/_generated/models/GetDatapointsResponse.py
honeyhive_bundled-1.0.1.dist-info/METADATA
honeyhive_bundled-1.0.1.dist-info/WHEEL
honeyhive_bundled-1.0.1.dist-info/entry_points.txt
honeyhive_bundled-1.0.1.dist-info/RECORD
