Metadata-Version: 2.4
Name: honeyhive-bundled
Version: 1.0.1
Summary: HoneyHive Python SDK (Bundled) - LLM Observability and Evaluation Platform with pre-release features
Project-URL: Homepage, https://honeyhive.ai
Project-URL: Documentation, https://docs.honeyhive.ai
Project-URL: Repository, https://github.com/honeyhiveai/python-sdk
Project-URL: Bug Tracker, https://github.com/honeyhiveai/python-sdk/issues
Author-email: HoneyHive Team <team@honeyhive.ai>
License: MIT
Keywords: ai,bundled,evaluation,llm,monitoring,observability,tracing
Classifier: Development Status :: 4 - Beta
Classifier: Intended Audience :: Developers
Classifier: License :: OSI Approved :: MIT License
Classifier: Operating System :: OS Independent
Classifier: Programming Language :: Python :: 3
Classifier: Programming Language :: Python :: 3.11
Classifier: Programming Language :: Python :: 3.12
Classifier: Programming Language :: Python :: 3.13
Classifier: Topic :: Software Development :: Libraries :: Python Modules
Classifier: Topic :: System :: Logging
Classifier: Topic :: System :: Monitoring
Requires-Python: >=3.11
Requires-Dist: click>=8.0.0
Requires-Dist: httpx>=0.24.0
Requires-Dist: opentelemetry-api>=1.20.0
Requires-Dist: opentelemetry-exporter-otlp-proto-http>=1.20.0
Requires-Dist: opentelemetry-sdk>=1.20.0
Requires-Dist: pydantic-settings>=2.0.0
Requires-Dist: pydantic>=2.0.0
Requires-Dist: python-dotenv>=1.0.0
Requires-Dist: pyyaml>=6.0
Requires-Dist: rich>=13.0.0
Requires-Dist: wrapt>=1.14.0
Provides-Extra: all-openinference
Requires-Dist: openinference-anthropic; extra == 'all-openinference'
Requires-Dist: openinference-aws-bedrock; extra == 'all-openinference'
Requires-Dist: openinference-azure-openai; extra == 'all-openinference'
Requires-Dist: openinference-google-adk; extra == 'all-openinference'
Requires-Dist: openinference-google-ai; extra == 'all-openinference'
Requires-Dist: openinference-mcp; extra == 'all-openinference'
Requires-Dist: openinference-openai; extra == 'all-openinference'
Provides-Extra: all-traceloop
Requires-Dist: traceloop-anthropic; extra == 'all-traceloop'
Requires-Dist: traceloop-aws-bedrock; extra == 'all-traceloop'
Requires-Dist: traceloop-azure-openai; extra == 'all-traceloop'
Requires-Dist: traceloop-google-ai; extra == 'all-traceloop'
Requires-Dist: traceloop-mcp; extra == 'all-traceloop'
Requires-Dist: traceloop-openai; extra == 'all-traceloop'
Provides-Extra: dev
Requires-Dist: beautifulsoup4>=4.12.0; extra == 'dev'
Requires-Dist: black==25.1.0; extra == 'dev'
Requires-Dist: build>=1.0.0; extra == 'dev'
Requires-Dist: docker>=7.0.0; extra == 'dev'
Requires-Dist: flake8>=6.0.0; extra == 'dev'
Requires-Dist: hatchling>=1.18.0; extra == 'dev'
Requires-Dist: isort==5.13.2; extra == 'dev'
Requires-Dist: mypy>=1.0.0; extra == 'dev'
Requires-Dist: openapi-python-generator>=2.1.0; extra == 'dev'
Requires-Dist: psutil>=5.9.0; extra == 'dev'
Requires-Dist: pytest-asyncio>=0.21.0; extra == 'dev'
Requires-Dist: pytest-cov>=7.0.0; extra == 'dev'
Requires-Dist: pytest-mock>=3.10.0; extra == 'dev'
Requires-Dist: pytest-xdist>=3.0.0; extra == 'dev'
Requires-Dist: pytest>=7.0.0; extra == 'dev'
Requires-Dist: requests>=2.31.0; extra == 'dev'
Requires-Dist: tox>=4.0.0; extra == 'dev'
Requires-Dist: typeguard>=4.0.0; extra == 'dev'
Requires-Dist: yamllint>=1.37.0; extra == 'dev'
Provides-Extra: docs
Requires-Dist: myst-parser>=2.0.0; extra == 'docs'
Requires-Dist: sphinx-rtd-theme>=1.3.0; extra == 'docs'
Requires-Dist: sphinx>=7.0.0; extra == 'docs'
Provides-Extra: openinference-anthropic
Requires-Dist: anthropic>=0.18.0; extra == 'openinference-anthropic'
Requires-Dist: openinference-instrumentation-anthropic>=0.1.0; extra == 'openinference-anthropic'
Provides-Extra: openinference-aws-bedrock
Requires-Dist: boto3>=1.26.0; extra == 'openinference-aws-bedrock'
Requires-Dist: openinference-instrumentation-bedrock>=0.1.0; extra == 'openinference-aws-bedrock'
Provides-Extra: openinference-azure-openai
Requires-Dist: azure-identity>=1.12.0; extra == 'openinference-azure-openai'
Requires-Dist: openai>=1.0.0; extra == 'openinference-azure-openai'
Requires-Dist: openinference-instrumentation-openai>=0.1.0; extra == 'openinference-azure-openai'
Provides-Extra: openinference-google-adk
Requires-Dist: google-adk>=0.1.0; extra == 'openinference-google-adk'
Requires-Dist: openinference-instrumentation-google-adk>=0.1.0; extra == 'openinference-google-adk'
Provides-Extra: openinference-google-ai
Requires-Dist: google-generativeai>=0.3.0; extra == 'openinference-google-ai'
Requires-Dist: openinference-instrumentation-google-generativeai>=0.1.0; extra == 'openinference-google-ai'
Provides-Extra: openinference-mcp
Requires-Dist: openinference-instrumentation-mcp>=1.3.0; extra == 'openinference-mcp'
Provides-Extra: openinference-openai
Requires-Dist: openai>=1.0.0; extra == 'openinference-openai'
Requires-Dist: openinference-instrumentation-openai>=0.1.0; extra == 'openinference-openai'
Provides-Extra: traceloop-anthropic
Requires-Dist: anthropic>=0.17.0; extra == 'traceloop-anthropic'
Requires-Dist: opentelemetry-instrumentation-anthropic<1.0.0,>=0.46.0; extra == 'traceloop-anthropic'
Provides-Extra: traceloop-aws-bedrock
Requires-Dist: boto3>=1.26.0; extra == 'traceloop-aws-bedrock'
Requires-Dist: opentelemetry-instrumentation-bedrock<1.0.0,>=0.46.0; extra == 'traceloop-aws-bedrock'
Provides-Extra: traceloop-azure-openai
Requires-Dist: azure-identity>=1.12.0; extra == 'traceloop-azure-openai'
Requires-Dist: openai>=1.0.0; extra == 'traceloop-azure-openai'
Requires-Dist: opentelemetry-instrumentation-openai<1.0.0,>=0.46.0; extra == 'traceloop-azure-openai'
Provides-Extra: traceloop-google-ai
Requires-Dist: google-generativeai>=0.3.0; extra == 'traceloop-google-ai'
Requires-Dist: opentelemetry-instrumentation-google-generativeai<1.0.0,>=0.46.0; extra == 'traceloop-google-ai'
Provides-Extra: traceloop-mcp
Requires-Dist: opentelemetry-instrumentation-mcp<1.0.0,>=0.46.0; extra == 'traceloop-mcp'
Provides-Extra: traceloop-openai
Requires-Dist: openai>=1.0.0; extra == 'traceloop-openai'
Requires-Dist: opentelemetry-instrumentation-openai<1.0.0,>=0.46.0; extra == 'traceloop-openai'
